{
  "uri": "/videos/272785535",
  "name": "REST Fest Midwest 2018 / Doug Dusseau / How do you do API Strategy and Evangelism?",
  "description": null,
  "link": "https://vimeo.com/272785535",
  "duration": 639,
  "width": 1280,
  "language": null,
  "height": 720,
  "embed": {
    "html": "<iframe src=\"https://player.vimeo.com/video/272785535?title=0&amp;byline=0&amp;portrait=0&amp;badge=0&amp;autopause=0&amp;player_id=0&amp;app_id=135039\" width=\"1280\" height=\"720\" frameborder=\"0\" allow=\"autoplay; fullscreen; picture-in-picture\" allowfullscreen title=\"REST Fest Midwest 2018 / Doug Dusseau / How do you do API Strategy and Evangelism?\"></iframe>",
    "badges": {
      "hdr": false,
      "live": {
        "streaming": false,
        "archived": false
      },
      "staff_pick": {
        "normal": false,
        "best_of_the_month": false,
        "best_of_the_year": false,
        "premiere": false
      },
      "vod": false,
      "weekend_challenge": false
    }
  },
  "created_time": "2018-05-31T15:10:12+00:00",
  "modified_time": "2020-02-08T23:37:54+00:00",
  "release_time": "2018-05-31T15:10:12+00:00",
  "license": "by-nc-sa",
  "pictures": {
    "uri": "/videos/272785535/pictures/704428020",
    "active": true,
    "type": "custom",
    "sizes": [
      {
        "width": 100,
        "height": 75,
        "link": "https://i.vimeocdn.com/video/704428020_100x75.jpg?r=pad",
        "link_with_play_button": "https://i.vimeocdn.com/filter/overlay?src0=https%3A%2F%2Fi.vimeocdn.com%2Fvideo%2F704428020_100x75.jpg&src1=http%3A%2F%2Ff.vimeocdn.com%2Fp%2Fimages%2Fcrawler_play.png"
      },
      {
        "width": 200,
        "height": 150,
        "link": "https://i.vimeocdn.com/video/704428020_200x150.jpg?r=pad",
        "link_with_play_button": "https://i.vimeocdn.com/filter/overlay?src0=https%3A%2F%2Fi.vimeocdn.com%2Fvideo%2F704428020_200x150.jpg&src1=http%3A%2F%2Ff.vimeocdn.com%2Fp%2Fimages%2Fcrawler_play.png"
      },
      {
        "width": 295,
        "height": 166,
        "link": "https://i.vimeocdn.com/video/704428020_295x166.jpg?r=pad",
        "link_with_play_button": "https://i.vimeocdn.com/filter/overlay?src0=https%3A%2F%2Fi.vimeocdn.com%2Fvideo%2F704428020_295x166.jpg&src1=http%3A%2F%2Ff.vimeocdn.com%2Fp%2Fimages%2Fcrawler_play.png"
      },
      {
        "width": 640,
        "height": 360,
        "link": "https://i.vimeocdn.com/video/704428020_640x360.jpg?r=pad",
        "link_with_play_button": "https://i.vimeocdn.com/filter/overlay?src0=https%3A%2F%2Fi.vimeocdn.com%2Fvideo%2F704428020_640x360.jpg&src1=http%3A%2F%2Ff.vimeocdn.com%2Fp%2Fimages%2Fcrawler_play.png"
      },
      {
        "width": 1280,
        "height": 720,
        "link": "https://i.vimeocdn.com/video/704428020_1280x720.jpg?r=pad",
        "link_with_play_button": "https://i.vimeocdn.com/filter/overlay?src0=https%3A%2F%2Fi.vimeocdn.com%2Fvideo%2F704428020_1280x720.jpg&src1=http%3A%2F%2Ff.vimeocdn.com%2Fp%2Fimages%2Fcrawler_play.png"
      },
      {
        "width": 1280,
        "height": 720,
        "link": "https://i.vimeocdn.com/video/704428020_1280x720.jpg?r=pad",
        "link_with_play_button": "https://i.vimeocdn.com/filter/overlay?src0=https%3A%2F%2Fi.vimeocdn.com%2Fvideo%2F704428020_1280x720.jpg&src1=http%3A%2F%2Ff.vimeocdn.com%2Fp%2Fimages%2Fcrawler_play.png"
      },
      {
        "width": 1280,
        "height": 720,
        "link": "https://i.vimeocdn.com/video/704428020_1280x720.jpg?r=pad",
        "link_with_play_button": "https://i.vimeocdn.com/filter/overlay?src0=https%3A%2F%2Fi.vimeocdn.com%2Fvideo%2F704428020_1280x720.jpg&src1=http%3A%2F%2Ff.vimeocdn.com%2Fp%2Fimages%2Fcrawler_play.png"
      },
      {
        "width": 1280,
        "height": 720,
        "link": "https://i.vimeocdn.com/video/704428020_1280x720.jpg?r=pad",
        "link_with_play_button": "https://i.vimeocdn.com/filter/overlay?src0=https%3A%2F%2Fi.vimeocdn.com%2Fvideo%2F704428020_1280x720.jpg&src1=http%3A%2F%2Ff.vimeocdn.com%2Fp%2Fimages%2Fcrawler_play.png"
      },
      {
        "width": 1920,
        "height": 1080,
        "link": "https://i.vimeocdn.com/video/704428020_1920x1080.jpg?r=pad",
        "link_with_play_button": "https://i.vimeocdn.com/filter/overlay?src0=https%3A%2F%2Fi.vimeocdn.com%2Fvideo%2F704428020_1920x1080.jpg&src1=http%3A%2F%2Ff.vimeocdn.com%2Fp%2Fimages%2Fcrawler_play.png"
      }
    ],
    "resource_key": "6f8a5f2e2e08168032765675200b305301814169",
    "default_picture": false
  }
}