{
	"login": "joelclermont",
	"id": 298100,
	"node_id": "MDQ6VXNlcjI5ODEwMA==",
	"avatar_url": "https://avatars0.githubusercontent.com/u/298100?v=4",
	"gravatar_id": "",
	"url": "https://api.github.com/users/joelclermont",
	"html_url": "https://github.com/joelclermont",
	"followers_url": "https://api.github.com/users/joelclermont/followers",
	"following_url": "https://api.github.com/users/joelclermont/following{/other_user}",
	"gists_url": "https://api.github.com/users/joelclermont/gists{/gist_id}",
	"starred_url": "https://api.github.com/users/joelclermont/starred{/owner}{/repo}",
	"subscriptions_url": "https://api.github.com/users/joelclermont/subscriptions",
	"organizations_url": "https://api.github.com/users/joelclermont/orgs",
	"repos_url": "https://api.github.com/users/joelclermont/repos",
	"events_url": "https://api.github.com/users/joelclermont/events{/privacy}",
	"received_events_url": "https://api.github.com/users/joelclermont/received_events",
	"type": "User",
	"site_admin": false,
	"name": "Joel Clermont",
	"company": null,
	"blog": "joelclermont.com",
	"location": "Milwaukee, WI",
	"email": null,
	"hireable": null,
	"bio": null,
	"public_repos": 62,
	"public_gists": 9,
	"followers": 46,
	"following": 5,
	"created_at": "2010-06-06T18:15:46Z",
	"updated_at": "2018-08-29T22:58:20Z"
}